libgencli/__init__.py
libgencli/cli.py
libgencli/common/__init__.py
libgencli/common/utils.py
libgencli/services/__init__.py
libgencli/services/libgen.py
libgencli-0.0.4.dist-info/LICENSE
libgencli-0.0.4.dist-info/METADATA
libgencli-0.0.4.dist-info/WHEEL
libgencli-0.0.4.dist-info/entry_points.txt
libgencli-0.0.4.dist-info/top_level.txt
libgencli-0.0.4.dist-info/RECORD
