Metadata-Version: 2.1
Name: libgencli
Version: 0.0.4
Summary: A command-line interface for searching and downloading books from Library Genesis.
Home-page: https://github.com/notjawad/libgencli
Author: notjawad
Author-email: chaptrhouse@gmail.com
Classifier: Programming Language :: Python :: 3
Classifier: License :: OSI Approved :: MIT License
Classifier: Operating System :: OS Independent
Requires-Python: >=3.7
License-File: LICENSE
Requires-Dist: aiohttp
Requires-Dist: questionary
Requires-Dist: tqdm
Requires-Dist: beautifulsoup4
